swmmRouting/__init__.py
swmmRouting/routing.py
swmmRouting/seeding.py
swmmrouting-0.0.3.dist-info/METADATA
swmmrouting-0.0.3.dist-info/WHEEL
swmmrouting-0.0.3.dist-info/licenses/LICENSE
swmmrouting-0.0.3.dist-info/RECORD
