Metadata-Version: 2.3
Name: swmmRouting
Version: 0.0.3
Summary: A package to route elements through a hydraulic network
Project-URL: Homepage, https://github.com/alBartig/swmmRouting
Project-URL: Issues, https://github.com/alBartig/swmmRouting/issues
Author-email: Albert Koenig <albert.koenig@tugraz.at>
Classifier: License :: OSI Approved :: MIT License
Classifier: Operating System :: OS Independent
Classifier: Programming Language :: Python :: 3
Requires-Python: >=3.07
